[
  {"id": 1, "name": "Nasi Goreng Spesial", "category": "Makanan Berat", "price": 22000, "rating": 4.8, "description": "Nasi goreng dengan telur, ayam suwir, dan acar segar.", "colorHex": "#FF6B35", "imageName": "nasi_goreng"},
  {"id": 2, "name": "Ayam Geprek Sambal", "category": "Makanan Berat", "price": 20000, "rating": 4.7, "description": "Ayam crispy digeprek dengan sambal bawang pedas.", "colorHex": "#E4551E", "imageName": "ayam_geprek"},
  {"id": 3, "name": "Mie Ayam Bakso", "category": "Makanan Berat", "price": 18000, "rating": 4.6, "description": "Mie ayam kuah gurih lengkap dengan bakso sapi.", "colorHex": "#2EC4B6", "imageName": "mie_ayam_baso"},
  {"id": 4, "name": "Sate Ayam Madura", "category": "Makanan Berat", "price": 25000, "rating": 4.9, "description": "Sate ayam bumbu kacang khas Madura, 10 tusuk.", "colorHex": "#FF9F1C", "imageName": "sate_ayam"},
  {"id": 5, "name": "Rendang Daging", "category": "Makanan Berat", "price": 28000, "rating": 4.9, "description": "Rendang daging sapi empuk dengan bumbu rempah khas Padang.", "colorHex": "#8B4513", "imageName": "rendang"},
  {"id": 6, "name": "Soto Ayam Lamongan", "category": "Makanan Berat", "price": 17000, "rating": 4.6, "description": "Soto ayam kuah kuning segar dengan koya gurih.", "colorHex": "#FFC107", "imageName": "soto_ayam"},
  {"id": 7, "name": "Gado-Gado Betawi", "category": "Makanan Berat", "price": 16000, "rating": 4.5, "description": "Sayuran segar dengan siraman bumbu kacang khas Betawi.", "colorHex": "#8BC34A", "imageName": "gado_gado"},
  {"id": 8, "name": "Nasi Padang Komplit", "category": "Makanan Berat", "price": 27000, "rating": 4.8, "description": "Nasi dengan lauk pilihan khas Padang, lengkap dan mengenyangkan.", "colorHex": "#D2691E", "imageName": "nasi_padang"},
  {"id": 9, "name": "Bakmi Jawa", "category": "Makanan Berat", "price": 19000, "rating": 4.5, "description": "Mie jawa digoreng dengan bumbu rempah dan telur.", "colorHex": "#A0522D", "imageName": "bakmi_jawa"},
  {"id": 10, "name": "Ikan Bakar Sambal Matah", "category": "Makanan Berat", "price": 26000, "rating": 4.7, "description": "Ikan bakar segar dengan sambal matah khas Bali.", "colorHex": "#FF7043", "imageName": "ikan_bakar"},

  {"id": 11, "name": "Es Teh Manis", "category": "Minuman", "price": 5000, "rating": 4.5, "description": "Teh manis dingin segar, cocok buat cuaca panas.", "colorHex": "#4CC9F0", "imageName": "es_teh"},
  {"id": 12, "name": "Es Jeruk Peras", "category": "Minuman", "price": 8000, "rating": 4.6, "description": "Jeruk peras asli tanpa pengawet.", "colorHex": "#F9C74F", "imageName": "es_jeruk"},
  {"id": 13, "name": "Es Kopi Susu Gula Aren", "category": "Minuman", "price": 15000, "rating": 4.8, "description": "Kopi susu dengan gula aren khas kekinian.", "colorHex": "#6F4E37", "imageName": "es_kopi"},
  {"id": 14, "name": "Jus Alpukat", "category": "Minuman", "price": 12000, "rating": 4.6, "description": "Jus alpukat creamy dengan topping coklat.", "colorHex": "#568203", "imageName": "jus_alpukat"},
  {"id": 15, "name": "Es Cendol", "category": "Minuman", "price": 10000, "rating": 4.5, "description": "Cendol segar dengan santan dan gula merah.", "colorHex": "#8FBC8F", "imageName": "es_cendol"},
  {"id": 16, "name": "Thai Tea", "category": "Minuman", "price": 13000, "rating": 4.7, "description": "Teh thai creamy dengan rasa khas.", "colorHex": "#FF8C69", "imageName": "thai_tea"},
  {"id": 17, "name": "Es Kelapa Muda", "category": "Minuman", "price": 11000, "rating": 4.6, "description": "Kelapa muda segar langsung dari buahnya.", "colorHex": "#87CEEB", "imageName": "es_kelapa"},
  {"id": 18, "name": "Jus Mangga", "category": "Minuman", "price": 12000, "rating": 4.5, "description": "Jus mangga manis dan segar.", "colorHex": "#FFA500", "imageName": "jus_mangga"},
  {"id": 19, "name": "Air Mineral", "category": "Minuman", "price": 4000, "rating": 4.3, "description": "Air mineral dingin kemasan botol.", "colorHex": "#B0E0E6", "imageName": "air_mineral"},
  {"id": 20, "name": "Milkshake Coklat", "category": "Minuman", "price": 16000, "rating": 4.7, "description": "Milkshake coklat creamy dengan whipped cream.", "colorHex": "#5C4033", "imageName": "milkshake_coklat"},

  {"id": 21, "name": "Risoles Mayo", "category": "Camilan", "price": 6000, "rating": 4.4, "description": "Risoles isi ragout ayam dengan topping mayones.", "colorHex": "#F3722C", "imageName": "risoles"},
  {"id": 22, "name": "Pisang Goreng Coklat", "category": "Camilan", "price": 7000, "rating": 4.3, "description": "Pisang goreng crispy dengan lelehan coklat.", "colorHex": "#90BE6D", "imageName": "pisang_goreng"},
  {"id": 23, "name": "Tahu Isi Sayur", "category": "Camilan", "price": 5000, "rating": 4.3, "description": "Tahu goreng isi sayuran segar.", "colorHex": "#DEB887", "imageName": "tahu_isi"},
  {"id": 24, "name": "Cireng Bumbu Rujak", "category": "Camilan", "price": 6000, "rating": 4.4, "description": "Cireng renyah disiram bumbu rujak pedas manis.", "colorHex": "#CD853F", "imageName": "cireng_rujak"},
  {"id": 25, "name": "Batagor Bandung", "category": "Camilan", "price": 12000, "rating": 4.6, "description": "Batagor dengan bumbu kacang khas Bandung.", "colorHex": "#8B7355", "imageName": "batagor"},
  {"id": 26, "name": "Siomay Ikan", "category": "Camilan", "price": 13000, "rating": 4.5, "description": "Siomay ikan dengan bumbu kacang dan kecap.", "colorHex": "#B8860B", "imageName": "siomay"},
  {"id": 27, "name": "Kentang Goreng", "category": "Camilan", "price": 10000, "rating": 4.4, "description": "Kentang goreng renyah dengan saus sambal.", "colorHex": "#DAA520", "imageName": "kentang_goreng"},
  {"id": 28, "name": "Roti Bakar Coklat Keju", "category": "Camilan", "price": 11000, "rating": 4.5, "description": "Roti bakar dengan topping coklat dan keju leleh.", "colorHex": "#D2691E", "imageName": "roti_bakar"},
  {"id": 29, "name": "Cimol Kriuk", "category": "Camilan", "price": 5000, "rating": 4.3, "description": "Cimol renyah dengan bumbu tabur pedas.", "colorHex": "#F4A460", "imageName": "cimol"},
  {"id": 30, "name": "Lumpia Semarang", "category": "Camilan", "price": 9000, "rating": 4.5, "description": "Lumpia isi rebung dan ayam khas Semarang.", "colorHex": "#DEB887", "imageName": "lumpia_semarang"},

  {"id": 31, "name": "Puding Coklat", "category": "Dessert", "price": 10000, "rating": 4.6, "description": "Puding coklat lembut dengan saus vla.", "colorHex": "#4B3621", "imageName": "puding_coklat"},
  {"id": 32, "name": "Es Krim Vanilla", "category": "Dessert", "price": 12000, "rating": 4.7, "description": "Es krim vanilla creamy dengan topping choco chip.", "colorHex": "#FFF8DC", "imageName": "eskrim"},
  {"id": 33, "name": "Brownies Panggang", "category": "Dessert", "price": 15000, "rating": 4.8, "description": "Brownies coklat panggang dengan tekstur fudgy.", "colorHex": "#3B2412", "imageName": "brownies"},
  {"id": 34, "name": "Cheesecake Slice", "category": "Dessert", "price": 18000, "rating": 4.9, "description": "Cheesecake lembut dengan topping berry.", "colorHex": "#FFF0DB", "imageName": "cheesecake"},
  {"id": 35, "name": "Tiramisu Cup", "category": "Dessert", "price": 17000, "rating": 4.8, "description": "Tiramisu klasik dengan lapisan kopi dan mascarpone.", "colorHex": "#6B4423", "imageName": "tiramisu"},
  {"id": 36, "name": "Es Campur", "category": "Dessert", "price": 13000, "rating": 4.5, "description": "Es campur segar dengan berbagai topping manis.", "colorHex": "#FF69B4", "imageName": "es_campur"},
  {"id": 37, "name": "Klepon", "category": "Dessert", "price": 8000, "rating": 4.4, "description": "Klepon isi gula merah dengan taburan kelapa.", "colorHex": "#228B22", "imageName": "klepon"},
  {"id": 38, "name": "Martabak Manis Mini", "category": "Dessert", "price": 14000, "rating": 4.7, "description": "Martabak manis mini dengan topping coklat keju.", "colorHex": "#DAA520", "imageName": "martabak"},
  {"id": 39, "name": "Panna Cotta", "category": "Dessert", "price": 16000, "rating": 4.6, "description": "Panna cotta lembut dengan saus mangga.", "colorHex": "#FFFACD", "imageName": "pannacotta"},
  {"id": 40, "name": "Waffle Madu", "category": "Dessert", "price": 15000, "rating": 4.7, "description": "Waffle renyah disiram madu dan buah segar.", "colorHex": "#F0E68C", "imageName": "waffle"},

  {"id": 41, "name": "Roti Coklat", "category": "Bakery", "price": 8000, "rating": 4.5, "description": "Roti lembut isi coklat melimpah.", "colorHex": "#5C4033", "imageName": "roti_coklat"},
  {"id": 42, "name": "Croissant Butter", "category": "Bakery", "price": 12000, "rating": 4.7, "description": "Croissant renyah dengan aroma butter yang khas.", "colorHex": "#F5DEB3", "imageName": "croissant"},
  {"id": 43, "name": "Donat Gula", "category": "Bakery", "price": 6000, "rating": 4.4, "description": "Donat lembut ditaburi gula halus.", "colorHex": "#FFDAB9", "imageName": "donatgula"},
  {"id": 44, "name": "Roti Sobek Keju", "category": "Bakery", "price": 10000, "rating": 4.6, "description": "Roti sobek lembut dengan taburan keju.", "colorHex": "#FFE4B5", "imageName": "rotikeju"},
  {"id": 45, "name": "Bagel Panggang", "category": "Bakery", "price": 11000, "rating": 4.5, "description": "Bagel panggang dengan tekstur kenyal khas.", "colorHex": "#DEB887", "imageName": "bagel"},
  {"id": 46, "name": "Muffin Blueberry", "category": "Bakery", "price": 13000, "rating": 4.6, "description": "Muffin lembut dengan buah blueberry segar.", "colorHex": "#4B0082", "imageName": "muffin"},
  {"id": 47, "name": "Roti Pisang Coklat", "category": "Bakery", "price": 9000, "rating": 4.5, "description": "Roti isi pisang dan coklat leleh.", "colorHex": "#8B4513", "imageName": "rotipisang"},
  {"id": 48, "name": "Danish Pastry", "category": "Bakery", "price": 14000, "rating": 4.7, "description": "Pastry berlapis dengan isian selai buah.", "colorHex": "#F4A460", "imageName": "danish"},
  {"id": 49, "name": "Roti Tawar Gandum", "category": "Bakery", "price": 12000, "rating": 4.4, "description": "Roti tawar gandum sehat untuk sarapan.", "colorHex": "#D2B48C", "imageName": "rotitawar"},
  {"id": 50, "name": "Cinnamon Roll", "category": "Bakery", "price": 13000, "rating": 4.8, "description": "Roti gulung kayu manis dengan glaze manis.", "colorHex": "#A0522D", "imageName": "cinnamonroll"}
]